{
  "project_info": {
    "project_number": "361067886943",
    "project_id": "attendify-app-kirpalamar",
    "storage_bucket": "attendify-app-kirpalamar.firebasestorage.app"
  },
  "client": [
    {
      "client_info": {
        "mobilesdk_app_id": "1:361067886943:android:cb7e38aab2f503796ddeea",
        "android_client_info": {
          "package_name": "com.edupilot360.attendify"
        }
      },
      "oauth_client": [],
      "api_key": [
        {
          "current_key": "AIzaSyAkEvqaBvhd1dJVZe3e__f8XkTHMJTKbBI"
        }
      ],
      "services": {
        "appinvite_service": {
          "other_platform_oauth_client": []
        }
      }
    },
    {
      "client_info": {
        "mobilesdk_app_id": "1:361067886943:android:37455d92cf3cbf0f6ddeea",
        "android_client_info": {
          "package_name": "com.example.attendify"
        }
      },
      "oauth_client": [],
      "api_key": [
        {
          "current_key": "AIzaSyAkEvqaBvhd1dJVZe3e__f8XkTHMJTKbBI"
        }
      ],
      "services": {
        "appinvite_service": {
          "other_platform_oauth_client": []
        }
      }
    }
  ],
  "configuration_version": "1"
}